mchat/__main__.py
mchat-0.1.0.dist-info/LICENSE
mchat-0.1.0.dist-info/WHEEL
mchat-0.1.0.dist-info/METADATA
mchat-0.1.0.dist-info/RECORD
