Metadata-Version: 2.1
Name: mchat
Version: 0.1.0
Summary: A console chat client for most Minecraft server versions
License: GPLv3
Author: Evan Pratten
Author-email: ewpratten@gmail.com
Requires-Python: >=3.9,<4.0
Classifier: License :: Other/Proprietary License
Classifier: Programming Language :: Python :: 3
Classifier: Programming Language :: Python :: 3.9
Requires-Dist: pycraft @ git+https://github.com/ammaraskar/pyCraft.git@master
Requires-Dist: rich (>=9.3.0,<10.0.0)
